<?xml version="1.0" encoding="utf-8"?>
<LanguageData>
  <ChangeDresser.label>魔法梳妝檯</ChangeDresser.label>
  <ChangeDresser.description>改變你的服裝顏色或存取服裝。</ChangeDresser.description>
  <ChangeDresser_Blueprint.label>魔法梳妝檯（藍圖）</ChangeDresser_Blueprint.label>
  <ChangeDresser_Blueprint_Install.label>魔法梳妝檯（藍圖）</ChangeDresser_Blueprint_Install.label>
  <ChangeDresser_Frame.label>魔法梳妝檯（建造中）</ChangeDresser_Frame.label>
  <ChangeDresser_Frame.description>改變你的服裝顏色或存取服裝。</ChangeDresser_Frame.description>
  <ChangeMirror.label>穿衣鏡</ChangeMirror.label>
  <ChangeMirror.description>化妝和染發。</ChangeMirror.description>
  <ChangeMirror_Blueprint.label>穿衣鏡（藍圖）</ChangeMirror_Blueprint.label>
  <ChangeMirror_Blueprint_Install.label>穿衣鏡（藍圖）</ChangeMirror_Blueprint_Install.label>
  <ChangeMirror_Frame.label>穿衣鏡（建造中）</ChangeMirror_Frame.label>
  <ChangeMirror_Frame.description>化妝和染發。</ChangeMirror_Frame.description>
  <RepairChangeDresser.label>修補裝置（服裝）</RepairChangeDresser.label>
  <RepairChangeDresser.description>一個可以修補梳妝檯內已存儲服裝的裝置。</RepairChangeDresser.description>
  <RepairChangeDresser_Blueprint.label>修補裝置（服裝）（藍圖）</RepairChangeDresser_Blueprint.label>
  <RepairChangeDresser_Blueprint_Install.label>修補裝置（服裝）（藍圖）</RepairChangeDresser_Blueprint_Install.label>
  <RepairChangeDresser_Frame.label>修補裝置（服裝）（建造中）</RepairChangeDresser_Frame.label>
  <RepairChangeDresser_Frame.description>一個可以修補梳妝檯內已存儲服裝的裝置。</RepairChangeDresser_Frame.description>
</LanguageData>